pyqtrapid/cli.py
pyqtrapid/main.py
pyqtrapid/src/__init__.py
pyqtrapid/src/mainwindow.py
pyqtrapid/src/appmodules/__init__.py
pyqtrapid-0.0.1.dist-info/LICENSE
pyqtrapid-0.0.1.dist-info/METADATA
pyqtrapid-0.0.1.dist-info/WHEEL
pyqtrapid-0.0.1.dist-info/entry_points.txt
pyqtrapid-0.0.1.dist-info/top_level.txt
pyqtrapid-0.0.1.dist-info/RECORD
